dhis2/__main__.py
dhis2/code_list/__init__.py
dhis2/code_list/cli.py
dhis2/code_list/icd10.py
dhis2/code_list/icd11.py
dhis2/code_list/models/__init__.py
dhis2/code_list/models/icd10.py
dhis2/code_list/models/icd11.py
dhis2/code_list/models/svcm.py
dhis2/code_list/svcm.py
dhis2/code_list/svcm_resources.py
dhis2/core/__init__.py
dhis2/core/cli.py
dhis2/core/http.py
dhis2/core/inspect.py
dhis2/core/inventory.py
dhis2/core/logging.py
dhis2/core/metadata/__init__.py
dhis2/core/metadata/models/__init__.py
dhis2/core/metadata/models/base.py
dhis2/core/metadata/models/property.py
dhis2/core/metadata/models/schema.py
dhis2/core/metadata/models/system_info.py
dhis2/core/utils.py
dhis2/e2b/cli.py
dhis2/e2b/common.py
dhis2/e2b/e2b_resources.py
dhis2/e2b/models/__init__.py
dhis2/e2b/models/e2b.py
dhis2/e2b/r2.py
dhis2/facility_list/__init__.py
dhis2/facility_list/cli.py
dhis2/facility_list/mcsd.py
dhis2/facility_list/mcsd_resources.py
dhis2/facility_list/models/__init__.py
dhis2/facility_list/models/mcsd.py
dhis2/generate/__init__.py
dhis2/generate/cli.py
dhis2/generate/json_schema.py
dhis2/generate/models/__init__.py
dhis2-0.7.5.dist-info/entry_points.txt
dhis2-0.7.5.dist-info/LICENSE
dhis2-0.7.5.dist-info/WHEEL
dhis2-0.7.5.dist-info/METADATA
dhis2-0.7.5.dist-info/RECORD
