Metadata-Version: 2.1
Name: dhis2
Version: 0.7.5
Summary: Tool for working and integrating with dhis2 instances
Home-page: https://github.com/dhis2/dhis2-python
License: BSD-3-Clause
Author: Morten Hansen
Author-email: morten@dhis2.org
Requires-Python: >=3.8,<4.0
Classifier: License :: OSI Approved :: BSD License
Classifier: Programming Language :: Python :: 3
Classifier: Programming Language :: Python :: 3.8
Classifier: Programming Language :: Python :: 3.9
Requires-Dist: PyYAML (>=5.3.1,<6.0.0)
Requires-Dist: click (>=7.1.2,<8.0.0)
Requires-Dist: fhir.resources (>=5.1.1,<6.0.0)
Requires-Dist: lxml (>=4.6.1,<5.0.0)
Requires-Dist: pydantic (>=1.7.2,<2.0.0)
Requires-Dist: requests (>=2.24.0,<3.0.0)
Project-URL: Bug Tracker, https://github.com/dhis2/dhis2-python/issues
Project-URL: Repository, https://github.com/dhis2/dhis2-python
Project-URL: Source, https://github.com/dhis2/dhis2-python
